searchproject/wordsearch.py
PyWordSearch-1.0.0.dist-info/LICENSE
PyWordSearch-1.0.0.dist-info/METADATA
PyWordSearch-1.0.0.dist-info/WHEEL
PyWordSearch-1.0.0.dist-info/top_level.txt
PyWordSearch-1.0.0.dist-info/RECORD
