Metadata-Version: 2.1
Name: PyWordSearch
Version: 1.0.0
Summary: A python package that solves word searches.
Home-page: https://github.com/clarkthepooh/pysearch/
Author: Clark Mattoon
License: MIT
Platform: UNKNOWN
Classifier: License :: OSI Approved :: MIT License
Classifier: Programming Language :: Python :: 3
Classifier: Programming Language :: Python :: 3.7
